sts_db_utils/__init__.py
sts_db_utils/sts_db_utils.py
sts_db_utils_tj-0.0.7.dist-info/METADATA
sts_db_utils_tj-0.0.7.dist-info/WHEEL
sts_db_utils_tj-0.0.7.dist-info/top_level.txt
sts_db_utils_tj-0.0.7.dist-info/RECORD
