Metadata-Version: 2.1
Name: sts-db-utils-tj
Version: 0.0.7
Summary: used to connect to the database
Home-page: https://github.com/tbindseil/sts-mono-repo
Author: tj
Author-email: tjbindseil@gmail.com
License: UNKNOWN
Platform: UNKNOWN
Classifier: Programming Language :: Python :: 3
Classifier: License :: OSI Approved :: MIT License
Classifier: Operating System :: OS Independent
Requires-Python: >=3.6
Requires-Dist: SQLAlchemy
Requires-Dist: boto3
